daraja_gateway/b2b.py
daraja_gateway/b2c.py
daraja_gateway/c2b.py
daraja_gateway/client.py
daraja_gateway/config.py
daraja_gateway/stk_push.py
daraja_gateway/token2.py
daraja_gateway/utils.py
daraja_gateway-0.1.0.dist-info/METADATA
daraja_gateway-0.1.0.dist-info/WHEEL
daraja_gateway-0.1.0.dist-info/top_level.txt
daraja_gateway-0.1.0.dist-info/RECORD
