Metadata-Version: 2.4
Name: daraja-gateway
Version: 0.1.0
Summary: A Python library for integrating with Safaricom Daraja API
Author: vincent mwangi kienje
Author-email: Vincent Mwangi Kienje <vynoroidtechnologies@gmail.com>
License: MIT
Project-URL: Homepage, https://github.com/yourusername/daraja-gateway
Project-URL: Repository, https://github.com/yourusername/daraja-gateway
Classifier: Programming Language :: Python :: 3
Classifier: License :: OSI Approved :: MIT License
Classifier: Operating System :: OS Independent
Requires-Python: >=3.7
Requires-Dist: Flask
Requires-Dist: requests
Dynamic: author
Dynamic: requires-python
